LICENSE
MANIFEST.in
README.md
setup.py
jsontp/__init__.py
jsontp/__main__.py
jsontp/config.py
jsontp/run.py
jsontp/utils.py
jsontp.egg-info/PKG-INFO
jsontp.egg-info/SOURCES.txt
jsontp.egg-info/dependency_links.txt
jsontp.egg-info/top_level.txt
tests/test_page_data_tree.py