Metadata-Version: 2.1
Name: jsontp
Version: 1.1.0
Summary: JSON Tree Parser
Home-page: https://pypi.org/project/jsontp
Download-URL: https://github.com/ames0k0/jsontp
Author: Nodaa Gaji
Author-email: c0d3r.nodiru.gaji@gmail.com
License: License :: OSI Approved :: MIT License
Platform: Operating System :: OS Independent
Classifier: Programming Language :: Python :: 3.10
License-File: LICENSE
